[
  {
    "name": "Design -1[c31]",
    "url": "https://github.com/hyper-sh/MyStorage/blob/main/Images/d1.png"
  },
  {
    "name": "Anime Night",
    "url": "https://cdn.jsdelivr.net/gh/hyper-sh/MyStorage@main/Images/anime-night.jpg"
  },
  {
    "name": "Mountain View",
    "url": "https://cdn.jsdelivr.net/gh/hyper-sh/MyStorage@main/Images/mountain.jpg"
  },
  {
    "name": "Cyberpunk",
    "url": "https://cdn.jsdelivr.net/gh/hyper-sh/MyStorage@main/Images/cyberpunk.jpg"
  },
  {
    "name": "Abstract Blue",
    "url": "https://cdn.jsdelivr.net/gh/hyper-sh/MyStorage@main/Images/abstract-blue.jpg"
  }
]
